{
  "version": 1,
  "projects": {
    "stampmaker": [
      {
        "href": "https://findly.tools/stampmaker?utm_source=stampmaker",
        "alt": "Featured on Findly.tools",
        "src": "https://findly.tools/badges/findly-tools-badge-light.svg",
        "width": 175,
        "height": 55
      },
      {
        "href": "https://turbo0.com/item/stamp-maker",
        "alt": "Listed on Turbo0",
        "src": "https://img.turbo0.com/badge-listed-light.svg",
        "width": 175,
        "height": 54
      },
      {
        "href": "https://twelve.tools",
        "alt": "Featured on Twelve Tools",
        "src": "https://twelve.tools/badge0-dark.svg",
        "width": 200,
        "height": 54
      },
      {
        "href": "https://aibesttop.com",
        "alt": "Listed on AIBestTop",
        "label": "Listed on AIBestTop"
      },
      {
        "href": "https://verifieddr.com/website/stampmaker-io",
        "alt": "Verified DR - Verified Domain Rating for www.stampmaker.io",
        "src": "https://verifieddr.com/badge/stampmaker-io.svg",
        "width": 220,
        "height": 68
      },
      {
        "href": "https://lovableapp.org",
        "alt": "Lovable App Badge",
        "src": "https://lovableapp.org/lovable-app-badge.svg",
        "width": 165,
        "height": 32
      },
      {
        "href": "https://yo.directory/",
        "alt": "yo.directory",
        "src": "https://cdn.prod.website-files.com/65c1546fa73ea974db789e3d/65e1e171f89ebfa7bd0129ac_yodirectory-featured.png",
        "width": 150,
        "height": 54
      },
      {
        "href": "https://artificin.com",
        "alt": "Featured on Artificin",
        "src": "https://artificin.com/badges/Artificin-badge.png",
        "width": 175,
        "height": 50
      },
      {
        "href": "https://startupfa.me/s/stampmaker.io-195?utm_source=www.stampmaker.io",
        "alt": "stampmaker.io - Featured on Startup Fame",
        "src": "https://startupfa.me/badges/featured-badge.webp",
        "width": 171,
        "height": 54
      },
      {
        "href": "https://toolfame.com/item/stamp-maker",
        "alt": "Featured on toolfame.com",
        "src": "https://toolfame.com/badge-light.svg",
        "width": 175,
        "height": 54
      },
      {
        "href": "https://aitoolfame.com/item/stamp-maker",
        "alt": "Featured on aitoolfame.com",
        "src": "https://aitoolfame.com/badge-light.svg",
        "width": 175,
        "height": 54
      },
      {
        "href": "https://fazier.com/launches/www.stampmaker.io",
        "alt": "Fazier badge",
        "src": "https://fazier.com/api/v1/public/badges/launch_badges.svg?badge_type=launched&theme=light",
        "width": 120
      },
      {
        "href": "https://saasfame.com/item/stamp-maker",
        "alt": "Featured on saasfame.com",
        "src": "https://saasfame.com/badge-light.svg",
        "height": 54
      },
      {
        "href": "https://dofollow.tools",
        "alt": "Featured on Dofollow.Tools",
        "src": "https://dofollow.tools/badge/badge_dark.svg",
        "width": 200,
        "height": 54
      }
    ],
    "mp3tourl": [
      {
        "href": "https://fazier.com/launches/www.mp3tourl.com",
        "alt": "mp3tourl on Fazier",
        "label": "mp3tourl on Fazier"
      },
      {
        "href": "https://findly.tools/mp3tourl?utm_source=mp3tourl",
        "alt": "mp3tourl on Findly Tools",
        "label": "mp3tourl on Findly Tools"
      },
      {
        "href": "https://indie.deals?ref=https%3A%2F%2Fwww.mp3tourl.com%2F",
        "alt": "mp3tourl on Indie.Deals",
        "label": "mp3tourl on Indie.Deals"
      },
      {
        "href": "https://startupfa.me/s/mp3tourl?utm_source=www.mp3tourl.com",
        "alt": "mp3tourl on Startup Fame",
        "label": "mp3tourl on Startup Fame"
      },
      {
        "href": "https://twelve.tools",
        "alt": "mp3tourl on Twelve Tools",
        "label": "mp3tourl on Twelve Tools"
      },
      {
        "href": "https://goodaitools.com",
        "alt": "mp3tourl on Good AI Tools",
        "label": "mp3tourl on Good AI Tools"
      },
      {
        "href": "https://showmebest.ai",
        "alt": "mp3tourl on ShowMeBestAI",
        "label": "mp3tourl on ShowMeBestAI"
      },
      {
        "href": "https://www.ontoplist.com/software-blogs/",
        "alt": "mp3tourl on OnTopList",
        "label": "mp3tourl on OnTopList"
      },
      {
        "href": "https://aidirs.org/item/mp3tourl",
        "alt": "mp3tourl on AIDirs",
        "label": "mp3tourl on AIDirs"
      },
      {
        "href": "https://submito.net",
        "alt": "mp3tourl on Submito",
        "label": "mp3tourl on Submito"
      },
      {
        "href": "https://turbo0.com/item/mp3tourl",
        "alt": "mp3tourl on Turbo0",
        "label": "mp3tourl on Turbo0"
      },
      {
        "href": "https://launchigniter.com/product/mp3tourl?ref=badge-mp3tourl",
        "alt": "mp3tourl on LaunchIgniter",
        "label": "mp3tourl on LaunchIgniter"
      },
      {
        "href": "https://dofollow.tools",
        "alt": "mp3tourl on Dofollow.Tools",
        "label": "mp3tourl on Dofollow.Tools"
      },
      {
        "href": "https://verifieddr.com/website/www-mp3tourl-com",
        "alt": "mp3tourl on Verified DR",
        "label": "mp3tourl on Verified DR"
      },
      {
        "href": "https://submitaitools.org",
        "alt": "mp3tourl on Submit AI Tools",
        "label": "mp3tourl on Submit AI Tools"
      }
    ],
    "videotourl": []
  }
}
